hisa/__init__.py
hisa/main.py
hisa-0.1.3.dist-info/LICENCE.txt
hisa-0.1.3.dist-info/METADATA
hisa-0.1.3.dist-info/WHEEL
hisa-0.1.3.dist-info/top_level.txt
hisa-0.1.3.dist-info/RECORD
