Metadata-Version: 2.1
Name: hisa
Version: 0.1.3
Summary: A python module that translates a number into Malagasy letters.
Home-page: https://github.com/rivo2302/Hisa
Author: rivo2302
Author-email: rivo.rajaonarivony@esti.mg
License: UNKNOWN
Project-URL: Bug Tracker, https://github.com/rivo2302/Hisa/issues
Keywords: MALAGASY,TRANSALATE,INTEGER
Platform: UNKNOWN
Classifier: Programming Language :: Python :: 3
Classifier: License :: OSI Approved :: MIT License
Classifier: Operating System :: OS Independent
Requires-Python: >=2.7
